[
  {
    "cssStyle": "height:440px; width:570px;", 
    "data": {
      "rows": [
        {
          "c": [
            {
              "v": 2000
            }, 
            {
              "f": "16.102", 
              "v": "16102"
            }, 
            {
              "f": "16.311", 
              "v": "16311"
            }
          ]
        }, 
        {
          "c": [
            {
              "v": 2001
            }, 
            {
              "f": "16.345", 
              "v": "16345"
            }, 
            {
              "f": "16.546", 
              "v": "16546"
            }
          ]
        }, 
        {
          "c": [
            {
              "v": 2002
            }, 
            {
              "f": "16.551", 
              "v": "16551"
            }, 
            {
              "f": "16.739", 
              "v": "16739"
            }
          ]
        }, 
        {
          "c": [
            {
              "v": 2003
            }, 
            {
              "f": "16.759", 
              "v": "16759"
            }, 
            {
              "f": "16.930", 
              "v": "16930"
            }
          ]
        }, 
        {
          "c": [
            {
              "v": 2004
            }, 
            {
              "f": "16.981", 
              "v": "16981"
            }, 
            {
              "f": "17.138", 
              "v": "17138"
            }
          ]
        }, 
        {
          "c": [
            {
              "v": 2005
            }, 
            {
              "f": "17.197", 
              "v": "17197"
            }, 
            {
              "f": "17.338", 
              "v": "17338"
            }
          ]
        }, 
        {
          "c": [
            {
              "v": 2006
            }, 
            {
              "f": "17.398", 
              "v": "17398"
            }, 
            {
              "f": "17.523", 
              "v": "17523"
            }
          ]
        }, 
        {
          "c": [
            {
              "v": 2007
            }, 
            {
              "f": "17.599", 
              "v": "17599"
            }, 
            {
              "f": "17.704", 
              "v": "17704"
            }
          ]
        }, 
        {
          "c": [
            {
              "v": 2008
            }, 
            {
              "f": "17.816", 
              "v": "17816"
            }, 
            {
              "f": "17.903", 
              "v": "17903"
            }
          ]
        }, 
        {
          "c": [
            {
              "v": 2009
            }, 
            {
              "f": "18.029", 
              "v": "18029"
            }, 
            {
              "f": "18.097", 
              "v": "18097"
            }
          ]
        }, 
        {
          "c": [
            {
              "v": 2010
            }, 
            {
              "f": "18.252", 
              "v": "18252"
            }, 
            {
              "f": "18.304", 
              "v": "18304"
            }
          ]
        }, 
        {
          "c": [
            {
              "v": 2011
            }, 
            {
              "f": "18.369", 
              "v": "18369"
            }, 
            {
              "f": "18.440", 
              "v": "18440"
            }
          ]
        }, 
        {
          "c": [
            {
              "v": 2012
            }, 
            {
              "f": "18.487", 
              "v": "18487"
            }, 
            {
              "f": "18.577", 
              "v": "18577"
            }
          ]
        }, 
        {
          "c": [
            {
              "v": 2013
            }, 
            {
              "f": "18.606", 
              "v": "18606"
            }, 
            {
              "f": "18.714", 
              "v": "18714"
            }
          ]
        }, 
        {
          "c": [
            {
              "v": 2014
            }, 
            {
              "f": "18.725", 
              "v": "18725"
            }, 
            {
              "f": "18.853", 
              "v": "18853"
            }
          ]
        }, 
        {
          "c": [
            {
              "v": 2015
            }, 
            {
              "f": "18.845", 
              "v": "18845"
            }, 
            {
              "f": "18.993", 
              "v": "18993"
            }
          ]
        }, 
        {
          "c": [
            {
              "v": 2016
            }, 
            {
              "f": "18.948", 
              "v": "18948"
            }, 
            {
              "f": "19.111", 
              "v": "19111"
            }
          ]
        }, 
        {
          "c": [
            {
              "v": 2017
            }, 
            {
              "f": "19.051", 
              "v": "19051"
            }, 
            {
              "f": "19.230", 
              "v": "19230"
            }
          ]
        }, 
        {
          "c": [
            {
              "v": 2018
            }, 
            {
              "f": "19.155", 
              "v": "19155"
            }, 
            {
              "f": "19.349", 
              "v": "19349"
            }
          ]
        }, 
        {
          "c": [
            {
              "v": 2019
            }, 
            {
              "f": "19.259", 
              "v": "19259"
            }, 
            {
              "f": "19.469", 
              "v": "19469"
            }
          ]
        }, 
        {
          "c": [
            {
              "v": 2020
            }, 
            {
              "f": "19.364", 
              "v": "19364"
            }, 
            {
              "f": "19.590", 
              "v": "19590"
            }
          ]
        }
      ], 
      "cols": [
        {
          "type": "string", 
          "id": "ano", 
          "label": "Ano"
        }, 
        {
          "type": "number", 
          "id": "v57", 
          "label": "Popula\u00e7\u00e3o Masculina"
        }, 
        {
          "type": "number", 
          "id": "v56", 
          "label": "Popula\u00e7\u00e3o Feminina"
        }
      ]
    }, 
    "type": "ColumnChart", 
    "options": {
      "isStacked": "true", 
      "formatters": {}, 
      "hAxis": {
        "title": "Ano"
      }, 
      "title": "Popula\u00e7\u00e3o Masculina/Feminina", 
      "vAxis": {
        "gridlines": {
          "count": 6
        }, 
        "title": "Popula\u00e7\u00e3o"
      }, 
      "displayExactValues": true, 
      "displayed": true, 
      "legend": {
        "position": "top", 
        "maxLines": 1
      }, 
      "fill": 20
    }
  }, 
  {
    "cssStyle": "height:440px; width:570px;", 
    "data": {
      "rows": [
        {
          "c": [
            {
              "v": "2000/2010"
            }, 
            {
              "f": "1,21", 
              "v": "1.21"
            }, 
            {
              "f": "", 
              "v": 0
            }
          ]
        }, 
        {
          "c": [
            {
              "v": "2010/2020"
            }, 
            {
              "f": "", 
              "v": 0
            }, 
            {
              "f": "0,64", 
              "v": "0.64"
            }
          ]
        }
      ], 
      "cols": [
        {
          "type": "string", 
          "id": "var", 
          "label": "Variavel"
        }, 
        {
          "type": "number", 
          "id": "valor", 
          "label": "Valor"
        }
      ]
    }, 
    "type": "BarChart", 
    "options": {
      "isStacked": "true", 
      "formatters": {}, 
      "hAxis": {
        "title": "variavel"
      }, 
      "title": "Taxa Geometrica de Crescimento Anual da Popula\u00e7\u00e3o", 
      "vAxis": {
        "gridlines": {
          "count": 6
        }, 
        "title": "Taxa de Crescimento"
      }, 
      "displayExactValues": true, 
      "displayed": true, 
      "legend": {
        "position": "none"
      }, 
      "fill": 20
    }
  }, 
  {
    "cssStyle": "height:440px; width:570px;", 
    "data": {
      "rows": [
        {
          "c": [
            {
              "v": "2000"
            }, 
            {
              "f": "1.931", 
              "v": "1931"
            }, 
            {
              "f": "2.371", 
              "v": "2371"
            }, 
            {
              "f": "1.777", 
              "v": "1777"
            }
          ]
        }, 
        {
          "c": [
            {
              "v": "2001"
            }, 
            {
              "f": "1.921", 
              "v": "1921"
            }, 
            {
              "f": "2.356", 
              "v": "2356"
            }, 
            {
              "f": "1.772", 
              "v": "1772"
            }
          ]
        }, 
        {
          "c": [
            {
              "v": "2002"
            }, 
            {
              "f": "1.908", 
              "v": "1908"
            }, 
            {
              "f": "2.336", 
              "v": "2336"
            }, 
            {
              "f": "1.760", 
              "v": "1760"
            }
          ]
        }, 
        {
          "c": [
            {
              "v": "2003"
            }, 
            {
              "f": "1.898", 
              "v": "1898"
            }, 
            {
              "f": "2.316", 
              "v": "2316"
            }, 
            {
              "f": "1.749", 
              "v": "1749"
            }
          ]
        }, 
        {
          "c": [
            {
              "v": "2004"
            }, 
            {
              "f": "1.880", 
              "v": "1880"
            }, 
            {
              "f": "2.296", 
              "v": "2296"
            }, 
            {
              "f": "1.738", 
              "v": "1738"
            }
          ]
        }, 
        {
          "c": [
            {
              "v": "2005"
            }, 
            {
              "f": "1.868", 
              "v": "1868"
            }, 
            {
              "f": "2.276", 
              "v": "2276"
            }, 
            {
              "f": "1.729", 
              "v": "1729"
            }
          ]
        }, 
        {
          "c": [
            {
              "v": "2006"
            }, 
            {
              "f": "1.850", 
              "v": "1850"
            }, 
            {
              "f": "2.252", 
              "v": "2252"
            }, 
            {
              "f": "1.715", 
              "v": "1715"
            }
          ]
        }, 
        {
          "c": [
            {
              "v": "2007"
            }, 
            {
              "f": "1.835", 
              "v": "1835"
            }, 
            {
              "f": "2.227", 
              "v": "2227"
            }, 
            {
              "f": "1.701", 
              "v": "1701"
            }
          ]
        }, 
        {
          "c": [
            {
              "v": "2008"
            }, 
            {
              "f": "1.816", 
              "v": "1816"
            }, 
            {
              "f": "2.205", 
              "v": "2205"
            }, 
            {
              "f": "1.688", 
              "v": "1688"
            }
          ]
        }, 
        {
          "c": [
            {
              "v": "2009"
            }, 
            {
              "f": "1.801", 
              "v": "1801"
            }, 
            {
              "f": "2.182", 
              "v": "2182"
            }, 
            {
              "f": "1.676", 
              "v": "1676"
            }
          ]
        }, 
        {
          "c": [
            {
              "v": "2010"
            }, 
            {
              "f": "1.783", 
              "v": "1783"
            }, 
            {
              "f": "2.159", 
              "v": "2159"
            }, 
            {
              "f": "1.662", 
              "v": "1662"
            }
          ]
        }, 
        {
          "c": [
            {
              "v": "2011"
            }, 
            {
              "f": "1.785", 
              "v": "1785"
            }, 
            {
              "f": "2.127", 
              "v": "2127"
            }, 
            {
              "f": "1.655", 
              "v": "1655"
            }
          ]
        }, 
        {
          "c": [
            {
              "v": "2012"
            }, 
            {
              "f": "1.787", 
              "v": "1787"
            }, 
            {
              "f": "2.095", 
              "v": "2095"
            }, 
            {
              "f": "1.643", 
              "v": "1643"
            }
          ]
        }, 
        {
          "c": [
            {
              "v": "2013"
            }, 
            {
              "f": "1.786", 
              "v": "1786"
            }, 
            {
              "f": "2.063", 
              "v": "2063"
            }, 
            {
              "f": "1.634", 
              "v": "1634"
            }
          ]
        }
      ], 
      "cols": [
        {
          "type": "string", 
          "id": "ano", 
          "label": "Ano"
        }, 
        {
          "type": "number", 
          "id": "v1006", 
          "label": "0 a 3 Anos"
        }, 
        {
          "type": "number", 
          "id": "v1009", 
          "label": "11 a 14 Anos"
        }, 
        {
          "type": "number", 
          "id": "v1010", 
          "label": "15 a 17 Anos"
        }
      ]
    }, 
    "type": "ColumnChart", 
    "options": {
      "isStacked": "true", 
      "formatters": {}, 
      "hAxis": {
        "title": "Ano"
      }, 
      "title": "Popula\u00e7\u00e3o em Idade Escolar", 
      "vAxis": {
        "gridlines": {
          "count": 6
        }, 
        "title": "Popula\u00e7\u00e3o"
      }, 
      "displayExactValues": true, 
      "displayed": true, 
      "legend": {
        "position": "bottom", 
        "maxLines": 2
      }, 
      "fill": 20
    }
  }, 
  {
    "cssStyle": "height:440px; width:570px;", 
    "data": {
      "rows": [
        {
          "c": [
            {
              "v": "2000"
            }, 
            {
              "f": "209,62", 
              "v": "209.62"
            }, 
            {
              "f": "6.467,15", 
              "v": "6467.15"
            }
          ]
        }, 
        {
          "c": [
            {
              "v": "2001"
            }, 
            {
              "f": "254,60", 
              "v": "254.60"
            }, 
            {
              "f": "7.740,59", 
              "v": "7740.59"
            }
          ]
        }, 
        {
          "c": [
            {
              "v": "2002"
            }, 
            {
              "f": "328,18", 
              "v": "328.18"
            }, 
            {
              "f": "9.858,14", 
              "v": "9858.14"
            }
          ]
        }, 
        {
          "c": [
            {
              "v": "2003"
            }, 
            {
              "f": "385,93", 
              "v": "385.93"
            }, 
            {
              "f": "11.455,77", 
              "v": "11455.77"
            }
          ]
        }, 
        {
          "c": [
            {
              "v": "2004"
            }, 
            {
              "f": "353,42", 
              "v": "353.42"
            }, 
            {
              "f": "10.358,40", 
              "v": "10358.40"
            }
          ]
        }, 
        {
          "c": [
            {
              "v": "2005"
            }, 
            {
              "f": "456,44", 
              "v": "456.44"
            }, 
            {
              "f": "13.216,63", 
              "v": "13216.63"
            }
          ]
        }, 
        {
          "c": [
            {
              "v": "2006"
            }, 
            {
              "f": "724,80", 
              "v": "724.80"
            }, 
            {
              "f": "20.755,43", 
              "v": "20755.43"
            }
          ]
        }, 
        {
          "c": [
            {
              "v": "2007"
            }, 
            {
              "f": "587,18", 
              "v": "587.18"
            }, 
            {
              "f": "16.632,53", 
              "v": "16632.53"
            }
          ]
        }, 
        {
          "c": [
            {
              "v": "2008"
            }, 
            {
              "f": "675,50", 
              "v": "675.50"
            }, 
            {
              "f": "18.911,38", 
              "v": "18911.38"
            }
          ]
        }, 
        {
          "c": [
            {
              "v": "2009"
            }, 
            {
              "f": "781,38", 
              "v": "781.38"
            }, 
            {
              "f": "21.629,42", 
              "v": "21629.42"
            }
          ]
        }, 
        {
          "c": [
            {
              "v": "2010"
            }, 
            {
              "f": "939,54", 
              "v": "939.54"
            }, 
            {
              "f": "25.701,32", 
              "v": "25701.32"
            }
          ]
        }, 
        {
          "c": [
            {
              "v": "2011"
            }, 
            {
              "f": "884,42", 
              "v": "884.42"
            }, 
            {
              "f": "24.027,25", 
              "v": "24027.25"
            }
          ]
        }
      ], 
      "cols": [
        {
          "type": "string", 
          "id": "ano", 
          "label": "Ano"
        }, 
        {
          "type": "number", 
          "id": "v1016", 
          "label": "PIB"
        }, 
        {
          "type": "number", 
          "id": "v1017", 
          "label": "PIB per Capita"
        }
      ]
    }, 
    "type": "ComboChart", 
    "options": {
      "hAxis": {
        "showTextEvery": 4, 
        "title": "Ano"
      }, 
      "title": "PIB e PIP per Capta", 
      "series": {
        "0": {
          "targetAxisIndex": 0, 
          "type": "bar"
        }, 
        "1": {
          "targetAxisIndex": 1, 
          "type": "line"
        }
      }, 
      "displayed": true, 
      "legend": {
        "position": "bottom", 
        "maxLines": 2
      }, 
      "vAxes": {
        "0": {
          "logScale": false
        }, 
        "1": {
          "logScale": false
        }
      }, 
      "seriesType": "bars"
    }
  }, 
  {
    "cssStyle": "height:440px; width:570px;", 
    "data": {
      "rows": [
        {
          "c": [
            {
              "v": 2000
            }, 
            {
              "f": "11,99", 
              "v": "11.99"
            }, 
            {
              "f": "27,12", 
              "v": "27.12"
            }, 
            {
              "f": "60,89", 
              "v": "60.89"
            }
          ]
        }, 
        {
          "c": [
            {
              "v": 2001
            }, 
            {
              "f": "17,79", 
              "v": "17.79"
            }, 
            {
              "f": "26,10", 
              "v": "26.10"
            }, 
            {
              "f": "56,11", 
              "v": "56.11"
            }
          ]
        }, 
        {
          "c": [
            {
              "v": 2002
            }, 
            {
              "f": "21,94", 
              "v": "21.94"
            }, 
            {
              "f": "27,19", 
              "v": "27.19"
            }, 
            {
              "f": "50,87", 
              "v": "50.87"
            }
          ]
        }, 
        {
          "c": [
            {
              "v": 2003
            }, 
            {
              "f": "18,81", 
              "v": "18.81"
            }, 
            {
              "f": "32,07", 
              "v": "32.07"
            }, 
            {
              "f": "49,12", 
              "v": "49.12"
            }
          ]
        }, 
        {
          "c": [
            {
              "v": 2004
            }, 
            {
              "f": "15,46", 
              "v": "15.46"
            }, 
            {
              "f": "30,25", 
              "v": "30.25"
            }, 
            {
              "f": "54,29", 
              "v": "54.29"
            }
          ]
        }, 
        {
          "c": [
            {
              "v": 2005
            }, 
            {
              "f": "13,53", 
              "v": "13.53"
            }, 
            {
              "f": "36,48", 
              "v": "36.48"
            }, 
            {
              "f": "49,99", 
              "v": "49.99"
            }
          ]
        }, 
        {
          "c": [
            {
              "v": 2006
            }, 
            {
              "f": "12,23", 
              "v": "12.23"
            }, 
            {
              "f": "20,68", 
              "v": "20.68"
            }, 
            {
              "f": "67,09", 
              "v": "67.09"
            }
          ]
        }, 
        {
          "c": [
            {
              "v": 2007
            }, 
            {
              "f": "12,36", 
              "v": "12.36"
            }, 
            {
              "f": "20,92", 
              "v": "20.92"
            }, 
            {
              "f": "66,72", 
              "v": "66.72"
            }
          ]
        }, 
        {
          "c": [
            {
              "v": 2008
            }, 
            {
              "f": "8,51", 
              "v": "8.51"
            }, 
            {
              "f": "21,58", 
              "v": "21.58"
            }, 
            {
              "f": "69,91", 
              "v": "69.91"
            }
          ]
        }, 
        {
          "c": [
            {
              "v": 2009
            }, 
            {
              "f": "9,27", 
              "v": "9.27"
            }, 
            {
              "f": "21,95", 
              "v": "21.95"
            }, 
            {
              "f": "68,78", 
              "v": "68.78"
            }
          ]
        }, 
        {
          "c": [
            {
              "v": 2010
            }, 
            {
              "f": "8,70", 
              "v": "8.70"
            }, 
            {
              "f": "23,50", 
              "v": "23.50"
            }, 
            {
              "f": "67,80", 
              "v": "67.80"
            }
          ]
        }, 
        {
          "c": [
            {
              "v": 2011
            }, 
            {
              "f": "12,48", 
              "v": "12.48"
            }, 
            {
              "f": "26,02", 
              "v": "26.02"
            }, 
            {
              "f": "61,50", 
              "v": "61.50"
            }
          ]
        }
      ], 
      "cols": [
        {
          "type": "string", 
          "id": "ano", 
          "label": "Ano"
        }, 
        {
          "type": "number", 
          "id": "v1495", 
          "label": "Agropecu\u00e1ria"
        }, 
        {
          "type": "number", 
          "id": "v1496", 
          "label": "Ind\u00fastria"
        }, 
        {
          "type": "number", 
          "id": "v1497", 
          "label": "Servi\u00e7os"
        }
      ]
    }, 
    "type": "LineChart", 
    "options": {
      "formatters": {}, 
      "hAxis": {
        "title": "Ano"
      }, 
      "title": "Participa\u00e7\u00e3o dos setores no Total do Valor Adicionado", 
      "vAxis": {
        "gridlines": {
          "count": 6
        }, 
        "title": "Participa\u00e7\u00e3o em %"
      }, 
      "displayExactValues": true, 
      "displayed": true, 
      "legend": {
        "position": "bottom", 
        "maxLines": 2
      }, 
      "fill": 20
    }
  }, 
  {
    "cssStyle": "height:440px; width:570px;", 
    "data": {
      "rows": [
        {
          "c": [
            {
              "v": 2000
            }, 
            {
              "f": "23,87", 
              "v": "23.87"
            }, 
            {
              "f": "15,09", 
              "v": "15.09"
            }, 
            {
              "f": "27,67", 
              "v": "27.67"
            }, 
            {
              "f": "32,53", 
              "v": "32.53"
            }
          ]
        }, 
        {
          "c": [
            {
              "v": 2001
            }, 
            {
              "f": "21,79", 
              "v": "21.79"
            }, 
            {
              "f": "15,00", 
              "v": "15.00"
            }, 
            {
              "f": "30,28", 
              "v": "30.28"
            }, 
            {
              "f": "31,96", 
              "v": "31.96"
            }
          ]
        }, 
        {
          "c": [
            {
              "v": 2002
            }, 
            {
              "f": "22,08", 
              "v": "22.08"
            }, 
            {
              "f": "15,90", 
              "v": "15.90"
            }, 
            {
              "f": "30,25", 
              "v": "30.25"
            }, 
            {
              "f": "30,46", 
              "v": "30.46"
            }
          ]
        }, 
        {
          "c": [
            {
              "v": 2003
            }, 
            {
              "f": "21,83", 
              "v": "21.83"
            }, 
            {
              "f": "14,26", 
              "v": "14.26"
            }, 
            {
              "f": "34,14", 
              "v": "34.14"
            }, 
            {
              "f": "28,99", 
              "v": "28.99"
            }
          ]
        }, 
        {
          "c": [
            {
              "v": 2004
            }, 
            {
              "f": "19,28", 
              "v": "19.28"
            }, 
            {
              "f": "12,10", 
              "v": "12.10"
            }, 
            {
              "f": "27,69", 
              "v": "27.69"
            }, 
            {
              "f": "39,90", 
              "v": "39.90"
            }
          ]
        }, 
        {
          "c": [
            {
              "v": 2005
            }, 
            {
              "f": "23,75", 
              "v": "23.75"
            }, 
            {
              "f": "14,10", 
              "v": "14.10"
            }, 
            {
              "f": "30,96", 
              "v": "30.96"
            }, 
            {
              "f": "30,14", 
              "v": "30.14"
            }
          ]
        }, 
        {
          "c": [
            {
              "v": 2006
            }, 
            {
              "f": "26,0", 
              "v": "26.0"
            }, 
            {
              "f": "16,2", 
              "v": "16.2"
            }, 
            {
              "f": "22,5", 
              "v": "22.5"
            }, 
            {
              "f": "34,1", 
              "v": "34.1"
            }
          ]
        }, 
        {
          "c": [
            {
              "v": 2007
            }, 
            {
              "f": "22,1", 
              "v": "22.1"
            }, 
            {
              "f": "16,1", 
              "v": "16.1"
            }, 
            {
              "f": "22,1", 
              "v": "22.1"
            }, 
            {
              "f": "38,1", 
              "v": "38.1"
            }
          ]
        }, 
        {
          "c": [
            {
              "v": 2008
            }, 
            {
              "f": "23,3", 
              "v": "23.3"
            }, 
            {
              "f": "20,2", 
              "v": "20.2"
            }, 
            {
              "f": "29,7", 
              "v": "29.7"
            }, 
            {
              "f": "25,0", 
              "v": "25.0"
            }
          ]
        }, 
        {
          "c": [
            {
              "v": 2009
            }, 
            {
              "f": "21,0", 
              "v": "21.0"
            }, 
            {
              "f": "17,6", 
              "v": "17.6"
            }, 
            {
              "f": "27,1", 
              "v": "27.1"
            }, 
            {
              "f": "33,1", 
              "v": "33.1"
            }
          ]
        }, 
        {
          "c": [
            {
              "v": 2010
            }, 
            {
              "f": "19,8", 
              "v": "19.8"
            }, 
            {
              "f": "20,0", 
              "v": "20.0"
            }, 
            {
              "f": "25,5", 
              "v": "25.5"
            }, 
            {
              "f": "33,2", 
              "v": "33.2"
            }
          ]
        }, 
        {
          "c": [
            {
              "v": 2011
            }, 
            {
              "f": "20,2", 
              "v": "20.2"
            }, 
            {
              "f": "19,2", 
              "v": "19.2"
            }, 
            {
              "f": "24,0", 
              "v": "24.0"
            }, 
            {
              "f": "34,8", 
              "v": "34.8"
            }
          ]
        }, 
        {
          "c": [
            {
              "v": 2012
            }, 
            {
              "f": "20,02", 
              "v": "20.02"
            }, 
            {
              "f": "20,39", 
              "v": "20.39"
            }, 
            {
              "f": "24,88", 
              "v": "24.88"
            }, 
            {
              "f": "33,23", 
              "v": "33.23"
            }
          ]
        }
      ], 
      "cols": [
        {
          "type": "string", 
          "id": "ano", 
          "label": "Ano"
        }, 
        {
          "type": "number", 
          "id": "v1045", 
          "label": "Ind\u00fastria"
        }, 
        {
          "type": "number", 
          "id": "v1046", 
          "label": "Com\u00e9rcio Atacadista e Varejista e do Com\u00e9rcio e Repara\u00e7\u00e3o de Ve\u00edculos Automotores e Motocicletas"
        }, 
        {
          "type": "number", 
          "id": "v1047", 
          "label": "Servi\u00e7os"
        }, 
        {
          "type": "number", 
          "id": "v1475", 
          "label": "Agricultura, Pecu\u00e1ria, Produ\u00e7\u00e3o Florestal, Pesca e Aquicultura"
        }
      ]
    }, 
    "type": "ColumnChart", 
    "options": {
      "isStacked": false, 
      "formatters": {}, 
      "hAxis": {
        "title": "Ano"
      }, 
      "title": "Participa\u00e7\u00e3o dos Setores no Total dos Empregos Formais", 
      "vAxis": {
        "gridlines": {
          "count": 6
        }, 
        "title": "Participa\u00e7\u00e3o em %"
      }, 
      "displayExactValues": true, 
      "displayed": true, 
      "legend": {
        "position": "bottom", 
        "maxLines": 2
      }, 
      "fill": 20
    }
  }, 
  {
    "cssStyle": "height:440px; width:570px;", 
    "data": {
      "rows": [
        {
          "c": [
            {
              "v": "Riqueza"
            }, 
            {
              "f": "38", 
              "v": "38"
            }, 
            {
              "f": "41", 
              "v": "41"
            }
          ]
        }, 
        {
          "c": [
            {
              "v": "Longevidade"
            }, 
            {
              "f": "61", 
              "v": "61"
            }, 
            {
              "f": "65", 
              "v": "65"
            }
          ]
        }, 
        {
          "c": [
            {
              "v": "Escolaridade"
            }, 
            {
              "f": "49", 
              "v": "49"
            }, 
            {
              "f": "65", 
              "v": "65"
            }
          ]
        }
      ], 
      "cols": [
        {
          "type": "string", 
          "id": "var", 
          "label": "Variavel"
        }, 
        {
          "type": "number", 
          "id": "p2008", 
          "label": "2008"
        }, 
        {
          "type": "number", 
          "id": "p2010", 
          "label": "2010"
        }
      ]
    }, 
    "type": "BarChart", 
    "options": {
      "isStacked": false, 
      "formatters": {}, 
      "hAxis": {
        "title": "Ano"
      }, 
      "title": "Indice Paulista de Responsabilisade Social, Por Dimens\u00f5es", 
      "vAxis": {
        "gridlines": {
          "count": 6
        }, 
        "title": "Dimens\u00e3o"
      }, 
      "displayExactValues": true, 
      "displayed": true, 
      "legend": {
        "position": "bottom", 
        "maxLines": 2
      }, 
      "fill": 20
    }
  }, 
  {
    "cssStyle": "height:440px; width:570px;", 
    "data": {
      "rows": [
        {
          "c": [
            {
              "v": "IPVS \u0096 Grupo 1 \u0096 Baix\u00edssima Vulnerabilidade"
            }, 
            {
              "f": "-", 
              "v": 0.0
            }
          ]
        }, 
        {
          "c": [
            {
              "v": "IPVS \u0096 Grupo 2 \u0096 Vulnerabilidade Muito Baixa"
            }, 
            {
              "f": "41,4", 
              "v": 41.4
            }
          ]
        }, 
        {
          "c": [
            {
              "v": "IPVS \u0096 Grupo 3 \u0096 Vulnerabilidade Baixa"
            }, 
            {
              "f": "19,3", 
              "v": 19.3
            }
          ]
        }, 
        {
          "c": [
            {
              "v": "IPVS \u0096 Grupo 4 \u0096 Vulnerabilidade M\u00e9dia (Urbanos)"
            }, 
            {
              "f": "30,5", 
              "v": 30.5
            }
          ]
        }, 
        {
          "c": [
            {
              "v": "IPVS \u0096 Grupo 5 \u0096 Vulnerabilidade Alta (Urbanos)"
            }, 
            {
              "f": "8,8", 
              "v": 8.8
            }
          ]
        }, 
        {
          "c": [
            {
              "v": "IPVS \u0096 Grupo 6 \u0096 Vulnerabilidade Muito Alta (Aglomerados Subnormais Urbanos)"
            }, 
            {
              "f": "-", 
              "v": 0.0
            }
          ]
        }, 
        {
          "c": [
            {
              "v": "IPVS \u0096 Grupo 7 \u0096 Vulnerabilidade Alta (Rurais)"
            }, 
            {
              "f": "-", 
              "v": 0.0
            }
          ]
        }
      ], 
      "cols": [
        {
          "type": "string", 
          "label": "Variavel"
        }, 
        {
          "type": "number", 
          "label": "Valor"
        }
      ]
    }, 
    "type": "PieChart", 
    "options": {
      "legend": {
        "position": "bottom", 
        "maxLines": 7
      }, 
      "title": "Indice Paulista de Responsabilisade Social"
    }
  }, 
  {
    "cssStyle": "height:440px; width:570px;", 
    "data": {
      "rows": [
        {
          "c": [
            {
              "v": 2000
            }, 
            {
              "f": "", 
              "v": 0
            }
          ]
        }, 
        {
          "c": [
            {
              "v": 2001
            }, 
            {
              "f": "", 
              "v": 0
            }
          ]
        }, 
        {
          "c": [
            {
              "v": 2002
            }, 
            {
              "f": "", 
              "v": 0
            }
          ]
        }, 
        {
          "c": [
            {
              "v": 2003
            }, 
            {
              "f": "", 
              "v": 0
            }
          ]
        }, 
        {
          "c": [
            {
              "v": 2004
            }, 
            {
              "f": "91,70", 
              "v": "91.70"
            }
          ]
        }, 
        {
          "c": [
            {
              "v": 2005
            }, 
            {
              "f": "96,13", 
              "v": "96.13"
            }
          ]
        }, 
        {
          "c": [
            {
              "v": 2006
            }, 
            {
              "f": "95,19", 
              "v": "95.19"
            }
          ]
        }, 
        {
          "c": [
            {
              "v": 2007
            }, 
            {
              "f": "96,48", 
              "v": "96.48"
            }
          ]
        }, 
        {
          "c": [
            {
              "v": 2008
            }, 
            {
              "f": "97,51", 
              "v": "97.51"
            }
          ]
        }, 
        {
          "c": [
            {
              "v": 2009
            }, 
            {
              "f": "95,63", 
              "v": "95.63"
            }
          ]
        }, 
        {
          "c": [
            {
              "v": 2010
            }, 
            {
              "f": "97,32", 
              "v": "97.32"
            }
          ]
        }, 
        {
          "c": [
            {
              "v": 2011
            }, 
            {
              "f": "96,60", 
              "v": "96.60"
            }
          ]
        }, 
        {
          "c": [
            {
              "v": 2012
            }, 
            {
              "f": "", 
              "v": 0
            }
          ]
        }
      ], 
      "cols": [
        {
          "type": "string", 
          "id": "ano", 
          "label": "Ano"
        }, 
        {
          "type": "number", 
          "id": "v1028", 
          "label": "M\u00e3es que Tiveram Sete e Mais Consultas de Pr\u00e9-Natal"
        }
      ]
    }, 
    "type": "ColumnChart", 
    "options": {
      "formatters": {}, 
      "hAxis": {
        "title": "Ano"
      }, 
      "title": "M\u00e3es que Tiveram 7 ou Mais Consultas de Pre-natal", 
      "vAxis": {
        "gridlines": {
          "count": 6
        }, 
        "title": "em %"
      }, 
      "displayExactValues": true, 
      "displayed": true, 
      "legend": {
        "position": "none"
      }, 
      "fill": 20
    }
  }, 
  {
    "cssStyle": "height:440px; width:570px;", 
    "data": {
      "rows": [
        {
          "c": [
            {
              "v": 2000
            }, 
            {
              "f": "", 
              "v": 0
            }
          ]
        }, 
        {
          "c": [
            {
              "v": 2001
            }, 
            {
              "f": "", 
              "v": 0
            }
          ]
        }, 
        {
          "c": [
            {
              "v": 2002
            }, 
            {
              "f": "", 
              "v": 0
            }
          ]
        }, 
        {
          "c": [
            {
              "v": 2003
            }, 
            {
              "f": "", 
              "v": 0
            }
          ]
        }, 
        {
          "c": [
            {
              "v": 2004
            }, 
            {
              "f": "91,70", 
              "v": "91.70"
            }
          ]
        }, 
        {
          "c": [
            {
              "v": 2005
            }, 
            {
              "f": "96,13", 
              "v": "96.13"
            }
          ]
        }, 
        {
          "c": [
            {
              "v": 2006
            }, 
            {
              "f": "95,19", 
              "v": "95.19"
            }
          ]
        }, 
        {
          "c": [
            {
              "v": 2007
            }, 
            {
              "f": "96,48", 
              "v": "96.48"
            }
          ]
        }, 
        {
          "c": [
            {
              "v": 2008
            }, 
            {
              "f": "97,51", 
              "v": "97.51"
            }
          ]
        }, 
        {
          "c": [
            {
              "v": 2009
            }, 
            {
              "f": "95,63", 
              "v": "95.63"
            }
          ]
        }, 
        {
          "c": [
            {
              "v": 2010
            }, 
            {
              "f": "97,32", 
              "v": "97.32"
            }
          ]
        }, 
        {
          "c": [
            {
              "v": 2011
            }, 
            {
              "f": "96,60", 
              "v": "96.60"
            }
          ]
        }, 
        {
          "c": [
            {
              "v": 2012
            }, 
            {
              "f": "", 
              "v": 0
            }
          ]
        }
      ], 
      "cols": [
        {
          "type": "string", 
          "id": "ano", 
          "label": "Ano"
        }, 
        {
          "type": "number", 
          "id": "v1028", 
          "label": "M\u00e3es que Tiveram Sete e Mais Consultas de Pr\u00e9-Natal"
        }
      ]
    }, 
    "type": "LineChart", 
    "options": {
      "formatters": {}, 
      "hAxis": {
        "title": "Ano"
      }, 
      "title": "Taxa de Mortalidade Infantil", 
      "vAxis": {
        "gridlines": {
          "count": 6
        }, 
        "title": "em %"
      }, 
      "displayExactValues": true, 
      "displayed": true, 
      "legend": {
        "position": "none"
      }, 
      "fill": 20
    }
  }
]