[
  {
    "cssStyle": "height:440px; width:570px;", 
    "data": {
      "rows": [
        {
          "c": [
            {
              "v": 2000
            }, 
            {
              "f": "8.599", 
              "v": "8599"
            }, 
            {
              "f": "8.505", 
              "v": "8505"
            }
          ]
        }, 
        {
          "c": [
            {
              "v": 2001
            }, 
            {
              "f": "8.801", 
              "v": "8801"
            }, 
            {
              "f": "8.730", 
              "v": "8730"
            }
          ]
        }, 
        {
          "c": [
            {
              "v": 2002
            }, 
            {
              "f": "8.998", 
              "v": "8998"
            }, 
            {
              "f": "8.948", 
              "v": "8948"
            }
          ]
        }, 
        {
          "c": [
            {
              "v": 2003
            }, 
            {
              "f": "9.201", 
              "v": "9201"
            }, 
            {
              "f": "9.175", 
              "v": "9175"
            }
          ]
        }, 
        {
          "c": [
            {
              "v": 2004
            }, 
            {
              "f": "9.402", 
              "v": "9402"
            }, 
            {
              "f": "9.397", 
              "v": "9397"
            }
          ]
        }, 
        {
          "c": [
            {
              "v": 2005
            }, 
            {
              "f": "9.585", 
              "v": "9585"
            }, 
            {
              "f": "9.606", 
              "v": "9606"
            }
          ]
        }, 
        {
          "c": [
            {
              "v": 2006
            }, 
            {
              "f": "9.764", 
              "v": "9764"
            }, 
            {
              "f": "9.811", 
              "v": "9811"
            }
          ]
        }, 
        {
          "c": [
            {
              "v": 2007
            }, 
            {
              "f": "9.944", 
              "v": "9944"
            }, 
            {
              "f": "10.019", 
              "v": "10019"
            }
          ]
        }, 
        {
          "c": [
            {
              "v": 2008
            }, 
            {
              "f": "10.120", 
              "v": "10120"
            }, 
            {
              "f": "10.229", 
              "v": "10229"
            }
          ]
        }, 
        {
          "c": [
            {
              "v": 2009
            }, 
            {
              "f": "10.290", 
              "v": "10290"
            }, 
            {
              "f": "10.429", 
              "v": "10429"
            }
          ]
        }, 
        {
          "c": [
            {
              "v": 2010
            }, 
            {
              "f": "10.448", 
              "v": "10448"
            }, 
            {
              "f": "10.622", 
              "v": "10622"
            }
          ]
        }, 
        {
          "c": [
            {
              "v": 2011
            }, 
            {
              "f": "10.594", 
              "v": "10594"
            }, 
            {
              "f": "10.788", 
              "v": "10788"
            }
          ]
        }, 
        {
          "c": [
            {
              "v": 2012
            }, 
            {
              "f": "10.742", 
              "v": "10742"
            }, 
            {
              "f": "10.958", 
              "v": "10958"
            }
          ]
        }, 
        {
          "c": [
            {
              "v": 2013
            }, 
            {
              "f": "10.892", 
              "v": "10892"
            }, 
            {
              "f": "11.129", 
              "v": "11129"
            }
          ]
        }, 
        {
          "c": [
            {
              "v": 2014
            }, 
            {
              "f": "11.045", 
              "v": "11045"
            }, 
            {
              "f": "11.304", 
              "v": "11304"
            }
          ]
        }, 
        {
          "c": [
            {
              "v": 2015
            }, 
            {
              "f": "11.199", 
              "v": "11199"
            }, 
            {
              "f": "11.481", 
              "v": "11481"
            }
          ]
        }, 
        {
          "c": [
            {
              "v": 2016
            }, 
            {
              "f": "11.314", 
              "v": "11314"
            }, 
            {
              "f": "11.613", 
              "v": "11613"
            }
          ]
        }, 
        {
          "c": [
            {
              "v": 2017
            }, 
            {
              "f": "11.430", 
              "v": "11430"
            }, 
            {
              "f": "11.747", 
              "v": "11747"
            }
          ]
        }, 
        {
          "c": [
            {
              "v": 2018
            }, 
            {
              "f": "11.547", 
              "v": "11547"
            }, 
            {
              "f": "11.883", 
              "v": "11883"
            }
          ]
        }, 
        {
          "c": [
            {
              "v": 2019
            }, 
            {
              "f": "11.665", 
              "v": "11665"
            }, 
            {
              "f": "12.019", 
              "v": "12019"
            }
          ]
        }, 
        {
          "c": [
            {
              "v": 2020
            }, 
            {
              "f": "11.785", 
              "v": "11785"
            }, 
            {
              "f": "12.158", 
              "v": "12158"
            }
          ]
        }
      ], 
      "cols": [
        {
          "type": "string", 
          "id": "ano", 
          "label": "Ano"
        }, 
        {
          "type": "number", 
          "id": "v57", 
          "label": "Popula\u00e7\u00e3o Masculina"
        }, 
        {
          "type": "number", 
          "id": "v56", 
          "label": "Popula\u00e7\u00e3o Feminina"
        }
      ]
    }, 
    "type": "ColumnChart", 
    "options": {
      "isStacked": "true", 
      "formatters": {}, 
      "hAxis": {
        "title": "Ano"
      }, 
      "title": "Popula\u00e7\u00e3o Masculina/Feminina", 
      "vAxis": {
        "gridlines": {
          "count": 6
        }, 
        "title": "Popula\u00e7\u00e3o"
      }, 
      "displayExactValues": true, 
      "displayed": true, 
      "legend": {
        "position": "top", 
        "maxLines": 1
      }, 
      "fill": 20
    }
  }, 
  {
    "cssStyle": "height:440px; width:570px;", 
    "data": {
      "rows": [
        {
          "c": [
            {
              "v": "2000/2010"
            }, 
            {
              "f": "2,11", 
              "v": "2.11"
            }, 
            {
              "f": "", 
              "v": 0
            }
          ]
        }, 
        {
          "c": [
            {
              "v": "2010/2020"
            }, 
            {
              "f": "", 
              "v": 0
            }, 
            {
              "f": "1,29", 
              "v": "1.29"
            }
          ]
        }
      ], 
      "cols": [
        {
          "type": "string", 
          "id": "var", 
          "label": "Variavel"
        }, 
        {
          "type": "number", 
          "id": "valor", 
          "label": "Valor"
        }
      ]
    }, 
    "type": "BarChart", 
    "options": {
      "isStacked": "true", 
      "formatters": {}, 
      "hAxis": {
        "title": "variavel"
      }, 
      "title": "Taxa Geometrica de Crescimento Anual da Popula\u00e7\u00e3o", 
      "vAxis": {
        "gridlines": {
          "count": 6
        }, 
        "title": "Taxa de Crescimento"
      }, 
      "displayExactValues": true, 
      "displayed": true, 
      "legend": {
        "position": "none"
      }, 
      "fill": 20
    }
  }, 
  {
    "cssStyle": "height:440px; width:570px;", 
    "data": {
      "rows": [
        {
          "c": [
            {
              "v": "2000"
            }, 
            {
              "f": "1.157", 
              "v": "1157"
            }, 
            {
              "f": "1.276", 
              "v": "1276"
            }, 
            {
              "f": "931", 
              "v": "931"
            }
          ]
        }, 
        {
          "c": [
            {
              "v": "2001"
            }, 
            {
              "f": "1.149", 
              "v": "1149"
            }, 
            {
              "f": "1.300", 
              "v": "1300"
            }, 
            {
              "f": "951", 
              "v": "951"
            }
          ]
        }, 
        {
          "c": [
            {
              "v": "2002"
            }, 
            {
              "f": "1.140", 
              "v": "1140"
            }, 
            {
              "f": "1.322", 
              "v": "1322"
            }, 
            {
              "f": "973", 
              "v": "973"
            }
          ]
        }, 
        {
          "c": [
            {
              "v": "2003"
            }, 
            {
              "f": "1.126", 
              "v": "1126"
            }, 
            {
              "f": "1.344", 
              "v": "1344"
            }, 
            {
              "f": "995", 
              "v": "995"
            }
          ]
        }, 
        {
          "c": [
            {
              "v": "2004"
            }, 
            {
              "f": "1.117", 
              "v": "1117"
            }, 
            {
              "f": "1.366", 
              "v": "1366"
            }, 
            {
              "f": "1.016", 
              "v": "1016"
            }
          ]
        }, 
        {
          "c": [
            {
              "v": "2005"
            }, 
            {
              "f": "1.103", 
              "v": "1103"
            }, 
            {
              "f": "1.384", 
              "v": "1384"
            }, 
            {
              "f": "1.033", 
              "v": "1033"
            }
          ]
        }, 
        {
          "c": [
            {
              "v": "2006"
            }, 
            {
              "f": "1.091", 
              "v": "1091"
            }, 
            {
              "f": "1.403", 
              "v": "1403"
            }, 
            {
              "f": "1.053", 
              "v": "1053"
            }
          ]
        }, 
        {
          "c": [
            {
              "v": "2007"
            }, 
            {
              "f": "1.075", 
              "v": "1075"
            }, 
            {
              "f": "1.420", 
              "v": "1420"
            }, 
            {
              "f": "1.071", 
              "v": "1071"
            }
          ]
        }, 
        {
          "c": [
            {
              "v": "2008"
            }, 
            {
              "f": "1.056", 
              "v": "1056"
            }, 
            {
              "f": "1.436", 
              "v": "1436"
            }, 
            {
              "f": "1.088", 
              "v": "1088"
            }
          ]
        }, 
        {
          "c": [
            {
              "v": "2009"
            }, 
            {
              "f": "1.038", 
              "v": "1038"
            }, 
            {
              "f": "1.450", 
              "v": "1450"
            }, 
            {
              "f": "1.103", 
              "v": "1103"
            }
          ]
        }, 
        {
          "c": [
            {
              "v": "2010"
            }, 
            {
              "f": "1.020", 
              "v": "1020"
            }, 
            {
              "f": "1.464", 
              "v": "1464"
            }, 
            {
              "f": "1.118", 
              "v": "1118"
            }
          ]
        }, 
        {
          "c": [
            {
              "v": "2011"
            }, 
            {
              "f": "1.035", 
              "v": "1035"
            }, 
            {
              "f": "1.431", 
              "v": "1431"
            }, 
            {
              "f": "1.118", 
              "v": "1118"
            }
          ]
        }, 
        {
          "c": [
            {
              "v": "2012"
            }, 
            {
              "f": "1.051", 
              "v": "1051"
            }, 
            {
              "f": "1.397", 
              "v": "1397"
            }, 
            {
              "f": "1.122", 
              "v": "1122"
            }
          ]
        }, 
        {
          "c": [
            {
              "v": "2013"
            }, 
            {
              "f": "1.066", 
              "v": "1066"
            }, 
            {
              "f": "1.365", 
              "v": "1365"
            }, 
            {
              "f": "1.123", 
              "v": "1123"
            }
          ]
        }
      ], 
      "cols": [
        {
          "type": "string", 
          "id": "ano", 
          "label": "Ano"
        }, 
        {
          "type": "number", 
          "id": "v1006", 
          "label": "0 a 3 Anos"
        }, 
        {
          "type": "number", 
          "id": "v1009", 
          "label": "11 a 14 Anos"
        }, 
        {
          "type": "number", 
          "id": "v1010", 
          "label": "15 a 17 Anos"
        }
      ]
    }, 
    "type": "ColumnChart", 
    "options": {
      "isStacked": "true", 
      "formatters": {}, 
      "hAxis": {
        "title": "Ano"
      }, 
      "title": "Popula\u00e7\u00e3o em Idade Escolar", 
      "vAxis": {
        "gridlines": {
          "count": 6
        }, 
        "title": "Popula\u00e7\u00e3o"
      }, 
      "displayExactValues": true, 
      "displayed": true, 
      "legend": {
        "position": "bottom", 
        "maxLines": 2
      }, 
      "fill": 20
    }
  }, 
  {
    "cssStyle": "height:440px; width:570px;", 
    "data": {
      "rows": [
        {
          "c": [
            {
              "v": "2000"
            }, 
            {
              "f": "78,32", 
              "v": "78.32"
            }, 
            {
              "f": "4.579,02", 
              "v": "4579.02"
            }
          ]
        }, 
        {
          "c": [
            {
              "v": "2001"
            }, 
            {
              "f": "92,81", 
              "v": "92.81"
            }, 
            {
              "f": "5.294,29", 
              "v": "5294.29"
            }
          ]
        }, 
        {
          "c": [
            {
              "v": "2002"
            }, 
            {
              "f": "104,29", 
              "v": "104.29"
            }, 
            {
              "f": "5.811,50", 
              "v": "5811.50"
            }
          ]
        }, 
        {
          "c": [
            {
              "v": "2003"
            }, 
            {
              "f": "116,40", 
              "v": "116.40"
            }, 
            {
              "f": "6.334,28", 
              "v": "6334.28"
            }
          ]
        }, 
        {
          "c": [
            {
              "v": "2004"
            }, 
            {
              "f": "115,24", 
              "v": "115.24"
            }, 
            {
              "f": "6.130,06", 
              "v": "6130.06"
            }
          ]
        }, 
        {
          "c": [
            {
              "v": "2005"
            }, 
            {
              "f": "131,74", 
              "v": "131.74"
            }, 
            {
              "f": "6.864,82", 
              "v": "6864.82"
            }
          ]
        }, 
        {
          "c": [
            {
              "v": "2006"
            }, 
            {
              "f": "147,69", 
              "v": "147.69"
            }, 
            {
              "f": "7.544,88", 
              "v": "7544.88"
            }
          ]
        }, 
        {
          "c": [
            {
              "v": "2007"
            }, 
            {
              "f": "157,45", 
              "v": "157.45"
            }, 
            {
              "f": "7.887,10", 
              "v": "7887.10"
            }
          ]
        }, 
        {
          "c": [
            {
              "v": "2008"
            }, 
            {
              "f": "175,07", 
              "v": "175.07"
            }, 
            {
              "f": "8.603,27", 
              "v": "8603.27"
            }
          ]
        }, 
        {
          "c": [
            {
              "v": "2009"
            }, 
            {
              "f": "215,10", 
              "v": "215.10"
            }, 
            {
              "f": "10.381,79", 
              "v": "10381.79"
            }
          ]
        }, 
        {
          "c": [
            {
              "v": "2010"
            }, 
            {
              "f": "253,59", 
              "v": "253.59"
            }, 
            {
              "f": "12.035,36", 
              "v": "12035.36"
            }
          ]
        }, 
        {
          "c": [
            {
              "v": "2011"
            }, 
            {
              "f": "290,43", 
              "v": "290.43"
            }, 
            {
              "f": "13.582,73", 
              "v": "13582.73"
            }
          ]
        }
      ], 
      "cols": [
        {
          "type": "string", 
          "id": "ano", 
          "label": "Ano"
        }, 
        {
          "type": "number", 
          "id": "v1016", 
          "label": "PIB"
        }, 
        {
          "type": "number", 
          "id": "v1017", 
          "label": "PIB per Capita"
        }
      ]
    }, 
    "type": "ComboChart", 
    "options": {
      "hAxis": {
        "showTextEvery": 4, 
        "title": "Ano"
      }, 
      "title": "PIB e PIP per Capta", 
      "series": {
        "0": {
          "targetAxisIndex": 0, 
          "type": "bar"
        }, 
        "1": {
          "targetAxisIndex": 1, 
          "type": "line"
        }
      }, 
      "displayed": true, 
      "legend": {
        "position": "bottom", 
        "maxLines": 2
      }, 
      "vAxes": {
        "0": {
          "logScale": false
        }, 
        "1": {
          "logScale": false
        }
      }, 
      "seriesType": "bars"
    }
  }, 
  {
    "cssStyle": "height:440px; width:570px;", 
    "data": {
      "rows": [
        {
          "c": [
            {
              "v": 2000
            }, 
            {
              "f": "10,50", 
              "v": "10.50"
            }, 
            {
              "f": "15,96", 
              "v": "15.96"
            }, 
            {
              "f": "73,56", 
              "v": "73.56"
            }
          ]
        }, 
        {
          "c": [
            {
              "v": 2001
            }, 
            {
              "f": "13,10", 
              "v": "13.10"
            }, 
            {
              "f": "14,90", 
              "v": "14.90"
            }, 
            {
              "f": "71,99", 
              "v": "71.99"
            }
          ]
        }, 
        {
          "c": [
            {
              "v": 2002
            }, 
            {
              "f": "18,08", 
              "v": "18.08"
            }, 
            {
              "f": "15,39", 
              "v": "15.39"
            }, 
            {
              "f": "66,52", 
              "v": "66.52"
            }
          ]
        }, 
        {
          "c": [
            {
              "v": 2003
            }, 
            {
              "f": "16,96", 
              "v": "16.96"
            }, 
            {
              "f": "15,78", 
              "v": "15.78"
            }, 
            {
              "f": "67,27", 
              "v": "67.27"
            }
          ]
        }, 
        {
          "c": [
            {
              "v": 2004
            }, 
            {
              "f": "12,54", 
              "v": "12.54"
            }, 
            {
              "f": "16,20", 
              "v": "16.20"
            }, 
            {
              "f": "71,27", 
              "v": "71.27"
            }
          ]
        }, 
        {
          "c": [
            {
              "v": 2005
            }, 
            {
              "f": "13,81", 
              "v": "13.81"
            }, 
            {
              "f": "15,56", 
              "v": "15.56"
            }, 
            {
              "f": "70,63", 
              "v": "70.63"
            }
          ]
        }, 
        {
          "c": [
            {
              "v": 2006
            }, 
            {
              "f": "12,52", 
              "v": "12.52"
            }, 
            {
              "f": "16,37", 
              "v": "16.37"
            }, 
            {
              "f": "71,11", 
              "v": "71.11"
            }
          ]
        }, 
        {
          "c": [
            {
              "v": 2007
            }, 
            {
              "f": "12,20", 
              "v": "12.20"
            }, 
            {
              "f": "14,36", 
              "v": "14.36"
            }, 
            {
              "f": "73,45", 
              "v": "73.45"
            }
          ]
        }, 
        {
          "c": [
            {
              "v": 2008
            }, 
            {
              "f": "8,27", 
              "v": "8.27"
            }, 
            {
              "f": "14,37", 
              "v": "14.37"
            }, 
            {
              "f": "77,36", 
              "v": "77.36"
            }
          ]
        }, 
        {
          "c": [
            {
              "v": 2009
            }, 
            {
              "f": "8,60", 
              "v": "8.60"
            }, 
            {
              "f": "13,70", 
              "v": "13.70"
            }, 
            {
              "f": "77,70", 
              "v": "77.70"
            }
          ]
        }, 
        {
          "c": [
            {
              "v": 2010
            }, 
            {
              "f": "8,89", 
              "v": "8.89"
            }, 
            {
              "f": "15,66", 
              "v": "15.66"
            }, 
            {
              "f": "75,45", 
              "v": "75.45"
            }
          ]
        }, 
        {
          "c": [
            {
              "v": 2011
            }, 
            {
              "f": "8,12", 
              "v": "8.12"
            }, 
            {
              "f": "16,32", 
              "v": "16.32"
            }, 
            {
              "f": "75,56", 
              "v": "75.56"
            }
          ]
        }
      ], 
      "cols": [
        {
          "type": "string", 
          "id": "ano", 
          "label": "Ano"
        }, 
        {
          "type": "number", 
          "id": "v1495", 
          "label": "Agropecu\u00e1ria"
        }, 
        {
          "type": "number", 
          "id": "v1496", 
          "label": "Ind\u00fastria"
        }, 
        {
          "type": "number", 
          "id": "v1497", 
          "label": "Servi\u00e7os"
        }
      ]
    }, 
    "type": "LineChart", 
    "options": {
      "formatters": {}, 
      "hAxis": {
        "title": "Ano"
      }, 
      "title": "Participa\u00e7\u00e3o dos setores no Total do Valor Adicionado", 
      "vAxis": {
        "gridlines": {
          "count": 6
        }, 
        "title": "Participa\u00e7\u00e3o em %"
      }, 
      "displayExactValues": true, 
      "displayed": true, 
      "legend": {
        "position": "bottom", 
        "maxLines": 2
      }, 
      "fill": 20
    }
  }, 
  {
    "cssStyle": "height:440px; width:570px;", 
    "data": {
      "rows": [
        {
          "c": [
            {
              "v": 2000
            }, 
            {
              "f": "38,21", 
              "v": "38.21"
            }, 
            {
              "f": "18,18", 
              "v": "18.18"
            }, 
            {
              "f": "29,43", 
              "v": "29.43"
            }, 
            {
              "f": "11,75", 
              "v": "11.75"
            }
          ]
        }, 
        {
          "c": [
            {
              "v": 2001
            }, 
            {
              "f": "26,01", 
              "v": "26.01"
            }, 
            {
              "f": "22,56", 
              "v": "22.56"
            }, 
            {
              "f": "31,40", 
              "v": "31.40"
            }, 
            {
              "f": "12,59", 
              "v": "12.59"
            }
          ]
        }, 
        {
          "c": [
            {
              "v": 2002
            }, 
            {
              "f": "34,61", 
              "v": "34.61"
            }, 
            {
              "f": "22,43", 
              "v": "22.43"
            }, 
            {
              "f": "29,53", 
              "v": "29.53"
            }, 
            {
              "f": "11,24", 
              "v": "11.24"
            }
          ]
        }, 
        {
          "c": [
            {
              "v": 2003
            }, 
            {
              "f": "34,05", 
              "v": "34.05"
            }, 
            {
              "f": "23,10", 
              "v": "23.10"
            }, 
            {
              "f": "31,33", 
              "v": "31.33"
            }, 
            {
              "f": "10,02", 
              "v": "10.02"
            }
          ]
        }, 
        {
          "c": [
            {
              "v": 2004
            }, 
            {
              "f": "35,54", 
              "v": "35.54"
            }, 
            {
              "f": "22,84", 
              "v": "22.84"
            }, 
            {
              "f": "32,06", 
              "v": "32.06"
            }, 
            {
              "f": "8,58", 
              "v": "8.58"
            }
          ]
        }, 
        {
          "c": [
            {
              "v": 2005
            }, 
            {
              "f": "40,45", 
              "v": "40.45"
            }, 
            {
              "f": "17,66", 
              "v": "17.66"
            }, 
            {
              "f": "30,72", 
              "v": "30.72"
            }, 
            {
              "f": "9,87", 
              "v": "9.87"
            }
          ]
        }, 
        {
          "c": [
            {
              "v": 2006
            }, 
            {
              "f": "38,6", 
              "v": "38.6"
            }, 
            {
              "f": "18,2", 
              "v": "18.2"
            }, 
            {
              "f": "34,5", 
              "v": "34.5"
            }, 
            {
              "f": "8,2", 
              "v": "8.2"
            }
          ]
        }, 
        {
          "c": [
            {
              "v": 2007
            }, 
            {
              "f": "36,4", 
              "v": "36.4"
            }, 
            {
              "f": "20,7", 
              "v": "20.7"
            }, 
            {
              "f": "32,0", 
              "v": "32.0"
            }, 
            {
              "f": "7,9", 
              "v": "7.9"
            }
          ]
        }, 
        {
          "c": [
            {
              "v": 2008
            }, 
            {
              "f": "34,7", 
              "v": "34.7"
            }, 
            {
              "f": "22,5", 
              "v": "22.5"
            }, 
            {
              "f": "29,7", 
              "v": "29.7"
            }, 
            {
              "f": "8,3", 
              "v": "8.3"
            }
          ]
        }, 
        {
          "c": [
            {
              "v": 2009
            }, 
            {
              "f": "30,0", 
              "v": "30.0"
            }, 
            {
              "f": "21,6", 
              "v": "21.6"
            }, 
            {
              "f": "36,7", 
              "v": "36.7"
            }, 
            {
              "f": "5,8", 
              "v": "5.8"
            }
          ]
        }, 
        {
          "c": [
            {
              "v": 2010
            }, 
            {
              "f": "32,1", 
              "v": "32.1"
            }, 
            {
              "f": "21,4", 
              "v": "21.4"
            }, 
            {
              "f": "34,4", 
              "v": "34.4"
            }, 
            {
              "f": "5,4", 
              "v": "5.4"
            }
          ]
        }, 
        {
          "c": [
            {
              "v": 2011
            }, 
            {
              "f": "28,9", 
              "v": "28.9"
            }, 
            {
              "f": "21,1", 
              "v": "21.1"
            }, 
            {
              "f": "34,6", 
              "v": "34.6"
            }, 
            {
              "f": "4,7", 
              "v": "4.7"
            }
          ]
        }, 
        {
          "c": [
            {
              "v": 2012
            }, 
            {
              "f": "31,11", 
              "v": "31.11"
            }, 
            {
              "f": "24,40", 
              "v": "24.40"
            }, 
            {
              "f": "32,48", 
              "v": "32.48"
            }, 
            {
              "f": "5,40", 
              "v": "5.40"
            }
          ]
        }
      ], 
      "cols": [
        {
          "type": "string", 
          "id": "ano", 
          "label": "Ano"
        }, 
        {
          "type": "number", 
          "id": "v1045", 
          "label": "Ind\u00fastria"
        }, 
        {
          "type": "number", 
          "id": "v1046", 
          "label": "Com\u00e9rcio Atacadista e Varejista e do Com\u00e9rcio e Repara\u00e7\u00e3o de Ve\u00edculos Automotores e Motocicletas"
        }, 
        {
          "type": "number", 
          "id": "v1047", 
          "label": "Servi\u00e7os"
        }, 
        {
          "type": "number", 
          "id": "v1475", 
          "label": "Agricultura, Pecu\u00e1ria, Produ\u00e7\u00e3o Florestal, Pesca e Aquicultura"
        }
      ]
    }, 
    "type": "ColumnChart", 
    "options": {
      "isStacked": false, 
      "formatters": {}, 
      "hAxis": {
        "title": "Ano"
      }, 
      "title": "Participa\u00e7\u00e3o dos Setores no Total dos Empregos Formais", 
      "vAxis": {
        "gridlines": {
          "count": 6
        }, 
        "title": "Participa\u00e7\u00e3o em %"
      }, 
      "displayExactValues": true, 
      "displayed": true, 
      "legend": {
        "position": "bottom", 
        "maxLines": 2
      }, 
      "fill": 20
    }
  }, 
  {
    "cssStyle": "height:440px; width:570px;", 
    "data": {
      "rows": [
        {
          "c": [
            {
              "v": "Riqueza"
            }, 
            {
              "f": "30", 
              "v": "30"
            }, 
            {
              "f": "34", 
              "v": "34"
            }
          ]
        }, 
        {
          "c": [
            {
              "v": "Longevidade"
            }, 
            {
              "f": "63", 
              "v": "63"
            }, 
            {
              "f": "64", 
              "v": "64"
            }
          ]
        }, 
        {
          "c": [
            {
              "v": "Escolaridade"
            }, 
            {
              "f": "61", 
              "v": "61"
            }, 
            {
              "f": "59", 
              "v": "59"
            }
          ]
        }
      ], 
      "cols": [
        {
          "type": "string", 
          "id": "var", 
          "label": "Variavel"
        }, 
        {
          "type": "number", 
          "id": "p2008", 
          "label": "2008"
        }, 
        {
          "type": "number", 
          "id": "p2010", 
          "label": "2010"
        }
      ]
    }, 
    "type": "BarChart", 
    "options": {
      "isStacked": false, 
      "formatters": {}, 
      "hAxis": {
        "title": "Ano"
      }, 
      "title": "Indice Paulista de Responsabilisade Social, Por Dimens\u00f5es", 
      "vAxis": {
        "gridlines": {
          "count": 6
        }, 
        "title": "Dimens\u00e3o"
      }, 
      "displayExactValues": true, 
      "displayed": true, 
      "legend": {
        "position": "bottom", 
        "maxLines": 2
      }, 
      "fill": 20
    }
  }, 
  {
    "cssStyle": "height:440px; width:570px;", 
    "data": {
      "rows": [
        {
          "c": [
            {
              "v": "IPVS \u0096 Grupo 1 \u0096 Baix\u00edssima Vulnerabilidade"
            }, 
            {
              "f": "-", 
              "v": 0.0
            }
          ]
        }, 
        {
          "c": [
            {
              "v": "IPVS \u0096 Grupo 2 \u0096 Vulnerabilidade Muito Baixa"
            }, 
            {
              "f": "52,0", 
              "v": 52.0
            }
          ]
        }, 
        {
          "c": [
            {
              "v": "IPVS \u0096 Grupo 3 \u0096 Vulnerabilidade Baixa"
            }, 
            {
              "f": "25,6", 
              "v": 25.6
            }
          ]
        }, 
        {
          "c": [
            {
              "v": "IPVS \u0096 Grupo 4 \u0096 Vulnerabilidade M\u00e9dia (Urbanos)"
            }, 
            {
              "f": "2,9", 
              "v": 2.9
            }
          ]
        }, 
        {
          "c": [
            {
              "v": "IPVS \u0096 Grupo 5 \u0096 Vulnerabilidade Alta (Urbanos)"
            }, 
            {
              "f": "18,0", 
              "v": 18.0
            }
          ]
        }, 
        {
          "c": [
            {
              "v": "IPVS \u0096 Grupo 6 \u0096 Vulnerabilidade Muito Alta (Aglomerados Subnormais Urbanos)"
            }, 
            {
              "f": "-", 
              "v": 0.0
            }
          ]
        }, 
        {
          "c": [
            {
              "v": "IPVS \u0096 Grupo 7 \u0096 Vulnerabilidade Alta (Rurais)"
            }, 
            {
              "f": "1,4", 
              "v": 1.4
            }
          ]
        }
      ], 
      "cols": [
        {
          "type": "string", 
          "label": "Variavel"
        }, 
        {
          "type": "number", 
          "label": "Valor"
        }
      ]
    }, 
    "type": "PieChart", 
    "options": {
      "legend": {
        "position": "bottom", 
        "maxLines": 7
      }, 
      "title": "Indice Paulista de Responsabilisade Social"
    }
  }, 
  {
    "cssStyle": "height:440px; width:570px;", 
    "data": {
      "rows": [
        {
          "c": [
            {
              "v": 2000
            }, 
            {
              "f": "", 
              "v": 0
            }
          ]
        }, 
        {
          "c": [
            {
              "v": 2001
            }, 
            {
              "f": "", 
              "v": 0
            }
          ]
        }, 
        {
          "c": [
            {
              "v": 2002
            }, 
            {
              "f": "", 
              "v": 0
            }
          ]
        }, 
        {
          "c": [
            {
              "v": 2003
            }, 
            {
              "f": "", 
              "v": 0
            }
          ]
        }, 
        {
          "c": [
            {
              "v": 2004
            }, 
            {
              "f": "79,42", 
              "v": "79.42"
            }
          ]
        }, 
        {
          "c": [
            {
              "v": 2005
            }, 
            {
              "f": "73,61", 
              "v": "73.61"
            }
          ]
        }, 
        {
          "c": [
            {
              "v": 2006
            }, 
            {
              "f": "82,42", 
              "v": "82.42"
            }
          ]
        }, 
        {
          "c": [
            {
              "v": 2007
            }, 
            {
              "f": "79,55", 
              "v": "79.55"
            }
          ]
        }, 
        {
          "c": [
            {
              "v": 2008
            }, 
            {
              "f": "76,03", 
              "v": "76.03"
            }
          ]
        }, 
        {
          "c": [
            {
              "v": 2009
            }, 
            {
              "f": "84,35", 
              "v": "84.35"
            }
          ]
        }, 
        {
          "c": [
            {
              "v": 2010
            }, 
            {
              "f": "78,09", 
              "v": "78.09"
            }
          ]
        }, 
        {
          "c": [
            {
              "v": 2011
            }, 
            {
              "f": "80,70", 
              "v": "80.70"
            }
          ]
        }, 
        {
          "c": [
            {
              "v": 2012
            }, 
            {
              "f": "", 
              "v": 0
            }
          ]
        }
      ], 
      "cols": [
        {
          "type": "string", 
          "id": "ano", 
          "label": "Ano"
        }, 
        {
          "type": "number", 
          "id": "v1028", 
          "label": "M\u00e3es que Tiveram Sete e Mais Consultas de Pr\u00e9-Natal"
        }
      ]
    }, 
    "type": "ColumnChart", 
    "options": {
      "formatters": {}, 
      "hAxis": {
        "title": "Ano"
      }, 
      "title": "M\u00e3es que Tiveram 7 ou Mais Consultas de Pre-natal", 
      "vAxis": {
        "gridlines": {
          "count": 6
        }, 
        "title": "em %"
      }, 
      "displayExactValues": true, 
      "displayed": true, 
      "legend": {
        "position": "none"
      }, 
      "fill": 20
    }
  }, 
  {
    "cssStyle": "height:440px; width:570px;", 
    "data": {
      "rows": [
        {
          "c": [
            {
              "v": 2000
            }, 
            {
              "f": "", 
              "v": 0
            }
          ]
        }, 
        {
          "c": [
            {
              "v": 2001
            }, 
            {
              "f": "", 
              "v": 0
            }
          ]
        }, 
        {
          "c": [
            {
              "v": 2002
            }, 
            {
              "f": "", 
              "v": 0
            }
          ]
        }, 
        {
          "c": [
            {
              "v": 2003
            }, 
            {
              "f": "", 
              "v": 0
            }
          ]
        }, 
        {
          "c": [
            {
              "v": 2004
            }, 
            {
              "f": "79,42", 
              "v": "79.42"
            }
          ]
        }, 
        {
          "c": [
            {
              "v": 2005
            }, 
            {
              "f": "73,61", 
              "v": "73.61"
            }
          ]
        }, 
        {
          "c": [
            {
              "v": 2006
            }, 
            {
              "f": "82,42", 
              "v": "82.42"
            }
          ]
        }, 
        {
          "c": [
            {
              "v": 2007
            }, 
            {
              "f": "79,55", 
              "v": "79.55"
            }
          ]
        }, 
        {
          "c": [
            {
              "v": 2008
            }, 
            {
              "f": "76,03", 
              "v": "76.03"
            }
          ]
        }, 
        {
          "c": [
            {
              "v": 2009
            }, 
            {
              "f": "84,35", 
              "v": "84.35"
            }
          ]
        }, 
        {
          "c": [
            {
              "v": 2010
            }, 
            {
              "f": "78,09", 
              "v": "78.09"
            }
          ]
        }, 
        {
          "c": [
            {
              "v": 2011
            }, 
            {
              "f": "80,70", 
              "v": "80.70"
            }
          ]
        }, 
        {
          "c": [
            {
              "v": 2012
            }, 
            {
              "f": "", 
              "v": 0
            }
          ]
        }
      ], 
      "cols": [
        {
          "type": "string", 
          "id": "ano", 
          "label": "Ano"
        }, 
        {
          "type": "number", 
          "id": "v1028", 
          "label": "M\u00e3es que Tiveram Sete e Mais Consultas de Pr\u00e9-Natal"
        }
      ]
    }, 
    "type": "LineChart", 
    "options": {
      "formatters": {}, 
      "hAxis": {
        "title": "Ano"
      }, 
      "title": "Taxa de Mortalidade Infantil", 
      "vAxis": {
        "gridlines": {
          "count": 6
        }, 
        "title": "em %"
      }, 
      "displayExactValues": true, 
      "displayed": true, 
      "legend": {
        "position": "none"
      }, 
      "fill": 20
    }
  }
]