[
  {
    "cssStyle": "height:350px; width:425px;", 
    "data": {
      "rows": [
        {
          "c": [
            {
              "v": 2000
            }, 
            {
              "f": "11.437", 
              "v": "11437"
            }, 
            {
              "f": "10.883", 
              "v": "10883"
            }
          ]
        }, 
        {
          "c": [
            {
              "v": 2001
            }, 
            {
              "f": "11.568", 
              "v": "11568"
            }, 
            {
              "f": "10.973", 
              "v": "10973"
            }
          ]
        }, 
        {
          "c": [
            {
              "v": 2002
            }, 
            {
              "f": "11.691", 
              "v": "11691"
            }, 
            {
              "f": "11.058", 
              "v": "11058"
            }
          ]
        }, 
        {
          "c": [
            {
              "v": 2003
            }, 
            {
              "f": "11.812", 
              "v": "11812"
            }, 
            {
              "f": "11.126", 
              "v": "11126"
            }
          ]
        }, 
        {
          "c": [
            {
              "v": 2004
            }, 
            {
              "f": "11.912", 
              "v": "11912"
            }, 
            {
              "f": "11.189", 
              "v": "11189"
            }
          ]
        }, 
        {
          "c": [
            {
              "v": 2005
            }, 
            {
              "f": "12.015", 
              "v": "12015"
            }, 
            {
              "f": "11.252", 
              "v": "11252"
            }
          ]
        }, 
        {
          "c": [
            {
              "v": 2006
            }, 
            {
              "f": "12.130", 
              "v": "12130"
            }, 
            {
              "f": "11.321", 
              "v": "11321"
            }
          ]
        }, 
        {
          "c": [
            {
              "v": 2007
            }, 
            {
              "f": "12.244", 
              "v": "12244"
            }, 
            {
              "f": "11.393", 
              "v": "11393"
            }
          ]
        }, 
        {
          "c": [
            {
              "v": 2008
            }, 
            {
              "f": "12.361", 
              "v": "12361"
            }, 
            {
              "f": "11.467", 
              "v": "11467"
            }
          ]
        }, 
        {
          "c": [
            {
              "v": 2009
            }, 
            {
              "f": "12.472", 
              "v": "12472"
            }, 
            {
              "f": "11.536", 
              "v": "11536"
            }
          ]
        }, 
        {
          "c": [
            {
              "v": 2010
            }, 
            {
              "f": "12.591", 
              "v": "12591"
            }, 
            {
              "f": "11.612", 
              "v": "11612"
            }
          ]
        }, 
        {
          "c": [
            {
              "v": 2011
            }, 
            {
              "f": "12.657", 
              "v": "12657"
            }, 
            {
              "f": "11.696", 
              "v": "11696"
            }
          ]
        }, 
        {
          "c": [
            {
              "v": 2012
            }, 
            {
              "f": "12.724", 
              "v": "12724"
            }, 
            {
              "f": "11.780", 
              "v": "11780"
            }
          ]
        }, 
        {
          "c": [
            {
              "v": 2013
            }, 
            {
              "f": "12.791", 
              "v": "12791"
            }, 
            {
              "f": "11.865", 
              "v": "11865"
            }
          ]
        }, 
        {
          "c": [
            {
              "v": 2014
            }, 
            {
              "f": "12.858", 
              "v": "12858"
            }, 
            {
              "f": "11.950", 
              "v": "11950"
            }
          ]
        }, 
        {
          "c": [
            {
              "v": 2015
            }, 
            {
              "f": "12.925", 
              "v": "12925"
            }, 
            {
              "f": "12.036", 
              "v": "12036"
            }
          ]
        }, 
        {
          "c": [
            {
              "v": 2016
            }, 
            {
              "f": "12.990", 
              "v": "12990"
            }, 
            {
              "f": "12.112", 
              "v": "12112"
            }
          ]
        }, 
        {
          "c": [
            {
              "v": 2017
            }, 
            {
              "f": "13.053", 
              "v": "13053"
            }, 
            {
              "f": "12.189", 
              "v": "12189"
            }
          ]
        }, 
        {
          "c": [
            {
              "v": 2018
            }, 
            {
              "f": "13.118", 
              "v": "13118"
            }, 
            {
              "f": "12.266", 
              "v": "12266"
            }
          ]
        }, 
        {
          "c": [
            {
              "v": 2019
            }, 
            {
              "f": "13.182", 
              "v": "13182"
            }, 
            {
              "f": "12.344", 
              "v": "12344"
            }
          ]
        }, 
        {
          "c": [
            {
              "v": 2020
            }, 
            {
              "f": "13.246", 
              "v": "13246"
            }, 
            {
              "f": "12.422", 
              "v": "12422"
            }
          ]
        }
      ], 
      "cols": [
        {
          "type": "number", 
          "id": "valor", 
          "label": "Valor"
        }, 
        {
          "type": "number", 
          "id": "v57", 
          "label": "Popula\u00e7\u00e3o Masculina"
        }, 
        {
          "type": "number", 
          "id": "v56", 
          "label": "Popula\u00e7\u00e3o Feminina"
        }
      ]
    }, 
    "type": "ColumnChart", 
    "options": {
      "isStacked": "true", 
      "formatters": {}, 
      "hAxis": {
        "title": "Ano"
      }, 
      "title": "Popula\u00e7\u00e3o Masculina/Feminina", 
      "vAxis": {
        "gridlines": {
          "count": 6
        }, 
        "title": "Popula\u00e7\u00e3o"
      }, 
      "displayExactValues": true, 
      "displayed": true, 
      "legend": {
        "position": "top", 
        "maxLines": 1
      }, 
      "fill": 20
    }
  }, 
  {
    "cssStyle": "height:350px; width:425px;", 
    "data": {
      "rows": [
        {
          "c": [
            {
              "v": "2000/2010"
            }, 
            {
              "f": "0,81", 
              "v": "0.81"
            }, 
            {
              "f": "", 
              "v": 0
            }
          ]
        }, 
        {
          "c": [
            {
              "v": "2010/2020"
            }, 
            {
              "f": "", 
              "v": 0
            }, 
            {
              "f": "0,59", 
              "v": "0.59"
            }
          ]
        }
      ], 
      "cols": [
        {
          "type": "string", 
          "id": "var", 
          "label": "Variavel"
        }, 
        {
          "type": "number", 
          "id": "valor", 
          "label": "Valor"
        }
      ]
    }, 
    "type": "BarChart", 
    "options": {
      "isStacked": "true", 
      "formatters": {}, 
      "hAxis": {
        "title": "variavel"
      }, 
      "title": "Taxa Geometrica de Crescimento Anual da Popula\u00e7\u00e3o", 
      "vAxis": {
        "gridlines": {
          "count": 6
        }, 
        "title": "Taxa de Crescimento"
      }, 
      "displayExactValues": true, 
      "displayed": true, 
      "legend": {
        "position": "none"
      }, 
      "fill": 20
    }
  }, 
  {
    "cssStyle": "height:350px; width:425px;", 
    "data": {
      "rows": [
        {
          "c": [
            {
              "v": 2000
            }, 
            {
              "f": "1.385", 
              "v": "1385"
            }, 
            {
              "f": "1.623", 
              "v": "1623"
            }, 
            {
              "f": "1.287", 
              "v": "1287"
            }
          ]
        }, 
        {
          "c": [
            {
              "v": 2001
            }, 
            {
              "f": "1.361", 
              "v": "1361"
            }, 
            {
              "f": "1.619", 
              "v": "1619"
            }, 
            {
              "f": "1.281", 
              "v": "1281"
            }
          ]
        }, 
        {
          "c": [
            {
              "v": 2002
            }, 
            {
              "f": "1.336", 
              "v": "1336"
            }, 
            {
              "f": "1.616", 
              "v": "1616"
            }, 
            {
              "f": "1.274", 
              "v": "1274"
            }
          ]
        }, 
        {
          "c": [
            {
              "v": 2003
            }, 
            {
              "f": "1.310", 
              "v": "1310"
            }, 
            {
              "f": "1.609", 
              "v": "1609"
            }, 
            {
              "f": "1.263", 
              "v": "1263"
            }
          ]
        }, 
        {
          "c": [
            {
              "v": 2004
            }, 
            {
              "f": "1.285", 
              "v": "1285"
            }, 
            {
              "f": "1.600", 
              "v": "1600"
            }, 
            {
              "f": "1.252", 
              "v": "1252"
            }
          ]
        }, 
        {
          "c": [
            {
              "v": 2005
            }, 
            {
              "f": "1.255", 
              "v": "1255"
            }, 
            {
              "f": "1.591", 
              "v": "1591"
            }, 
            {
              "f": "1.240", 
              "v": "1240"
            }
          ]
        }, 
        {
          "c": [
            {
              "v": 2006
            }, 
            {
              "f": "1.230", 
              "v": "1230"
            }, 
            {
              "f": "1.581", 
              "v": "1581"
            }, 
            {
              "f": "1.231", 
              "v": "1231"
            }
          ]
        }, 
        {
          "c": [
            {
              "v": 2007
            }, 
            {
              "f": "1.205", 
              "v": "1205"
            }, 
            {
              "f": "1.572", 
              "v": "1572"
            }, 
            {
              "f": "1.220", 
              "v": "1220"
            }
          ]
        }, 
        {
          "c": [
            {
              "v": 2008
            }, 
            {
              "f": "1.178", 
              "v": "1178"
            }, 
            {
              "f": "1.562", 
              "v": "1562"
            }, 
            {
              "f": "1.209", 
              "v": "1209"
            }
          ]
        }, 
        {
          "c": [
            {
              "v": 2009
            }, 
            {
              "f": "1.152", 
              "v": "1152"
            }, 
            {
              "f": "1.550", 
              "v": "1550"
            }, 
            {
              "f": "1.196", 
              "v": "1196"
            }
          ]
        }, 
        {
          "c": [
            {
              "v": 2010
            }, 
            {
              "f": "1.129", 
              "v": "1129"
            }, 
            {
              "f": "1.541", 
              "v": "1541"
            }, 
            {
              "f": "1.185", 
              "v": "1185"
            }
          ]
        }, 
        {
          "c": [
            {
              "v": 2011
            }, 
            {
              "f": "1.140", 
              "v": "1140"
            }, 
            {
              "f": "1.490", 
              "v": "1490"
            }, 
            {
              "f": "1.168", 
              "v": "1168"
            }
          ]
        }, 
        {
          "c": [
            {
              "v": 2012
            }, 
            {
              "f": "1.152", 
              "v": "1152"
            }, 
            {
              "f": "1.440", 
              "v": "1440"
            }, 
            {
              "f": "1.154", 
              "v": "1154"
            }
          ]
        }, 
        {
          "c": [
            {
              "v": 2013
            }, 
            {
              "f": "1.162", 
              "v": "1162"
            }, 
            {
              "f": "1.391", 
              "v": "1391"
            }, 
            {
              "f": "1.138", 
              "v": "1138"
            }
          ]
        }, 
        {
          "c": [
            {
              "v": 2014
            }, 
            {
              "f": "1.173", 
              "v": "1173"
            }, 
            {
              "f": "1.344", 
              "v": "1344"
            }, 
            {
              "f": "1.121", 
              "v": "1121"
            }
          ]
        }, 
        {
          "c": [
            {
              "v": 2015
            }, 
            {
              "f": "1.183", 
              "v": "1183"
            }, 
            {
              "f": "1.297", 
              "v": "1297"
            }, 
            {
              "f": "1.104", 
              "v": "1104"
            }
          ]
        }, 
        {
          "c": [
            {
              "v": 2016
            }, 
            {
              "f": "1.183", 
              "v": "1183"
            }, 
            {
              "f": "1.264", 
              "v": "1264"
            }, 
            {
              "f": "1.064", 
              "v": "1064"
            }
          ]
        }, 
        {
          "c": [
            {
              "v": 2017
            }, 
            {
              "f": "1.183", 
              "v": "1183"
            }, 
            {
              "f": "1.232", 
              "v": "1232"
            }, 
            {
              "f": "1.024", 
              "v": "1024"
            }
          ]
        }, 
        {
          "c": [
            {
              "v": 2018
            }, 
            {
              "f": "1.177", 
              "v": "1177"
            }, 
            {
              "f": "1.200", 
              "v": "1200"
            }, 
            {
              "f": "984", 
              "v": "984"
            }
          ]
        }, 
        {
          "c": [
            {
              "v": 2019
            }, 
            {
              "f": "1.174", 
              "v": "1174"
            }, 
            {
              "f": "1.168", 
              "v": "1168"
            }, 
            {
              "f": "948", 
              "v": "948"
            }
          ]
        }, 
        {
          "c": [
            {
              "v": 2020
            }, 
            {
              "f": "1.173", 
              "v": "1173"
            }, 
            {
              "f": "1.138", 
              "v": "1138"
            }, 
            {
              "f": "910", 
              "v": "910"
            }
          ]
        }
      ], 
      "cols": [
        {
          "type": "number", 
          "id": "valor", 
          "label": "Valor"
        }, 
        {
          "type": "number", 
          "id": "v1006", 
          "label": "0 a 3 Anos"
        }, 
        {
          "type": "number", 
          "id": "v1009", 
          "label": "11 a 14 Anos"
        }, 
        {
          "type": "number", 
          "id": "v1010", 
          "label": "15 a 17 Anos"
        }
      ]
    }, 
    "type": "ColumnChart", 
    "options": {
      "isStacked": "true", 
      "formatters": {}, 
      "hAxis": {
        "title": "Ano"
      }, 
      "title": "Popula\u00e7\u00e3o em Idade Escolar", 
      "vAxis": {
        "gridlines": {
          "count": 6
        }, 
        "title": "Popula\u00e7\u00e3o"
      }, 
      "displayExactValues": true, 
      "displayed": true, 
      "legend": {
        "position": "bottom", 
        "maxLines": 2
      }, 
      "fill": 20
    }
  }
]